bashbuddy/__init__.py
bashbuddy/__main__.py
bashbuddy/agent.py
bashbuddy/config.py
bashbuddy/tools/__init__.py
bashbuddy/tools/file_tree.py
bashbuddy/tools/persistent_bash.py
bashbuddy-0.3.0.dist-info/LICENSE.md
bashbuddy-0.3.0.dist-info/METADATA
bashbuddy-0.3.0.dist-info/WHEEL
bashbuddy-0.3.0.dist-info/entry_points.txt
bashbuddy-0.3.0.dist-info/RECORD
