Metadata-Version: 2.1
Name: bashbuddy
Version: 0.3.0
Summary: Hook an LLM up to a Bash terminal
License: MIT
Author: Omegastick
Author-email: isaac@poulton.dev
Requires-Python: >=3.11,<4.0
Classifier: License :: OSI Approved :: MIT License
Classifier: Programming Language :: Python :: 3
Classifier: Programming Language :: Python :: 3.11
Requires-Dist: langchain (>=0.0.200,<0.0.201)
Requires-Dist: openai (>=0.27.8,<0.28.0)
Requires-Dist: platformdirs (>=3.2.0,<4.0.0)
Requires-Dist: pyfakefs (>=5.2.2,<6.0.0)
Requires-Dist: typer (>=0.9.0,<0.10.0)
